{
  "manifestVersion": "3.2",
  "proxies": [
    {
      "address": "0xFE721eA21F61e37477782eFCDaAE43dcb61c82E9",
      "txHash": "0x56685ff7278dc3c642bbe198807cda24b4f5958b4f042cbbd85f90dd612531c1",
      "kind": "transparent"
    }
  ],
  "impls": {
    "472c056c09b2c2bba804837b8870cf765e7f0273c13567127dba807fe19ed08f": {
      "address": "0x5A43CB5f9bfef2b299b5b93f96098De7273ad134",
      "txHash": "0xf4c669182f327aae637e716248ce1596fdfdc73fa5baa5fe95385e23dfdab812",
      "layout": {
        "solcVersion": "0.8.20",
        "storage": [
          {
            "label": "message",
            "offset": 0,
            "slot": "0",
            "type": "t_string_storage",
            "contract": "Swisstronik",
            "src": "contracts/Hello_swtr.sol:5"
          }
        ],
        "types": {
          "t_string_storage": {
            "label": "string",
            "numberOfBytes": "32"
          }
        },
        "namespaces": {}
      }
    }
  }
}
